IREX/Funciones.py
IREX/__init__.py
IREX-1.0.0.dist-info/METADATA
IREX-1.0.0.dist-info/WHEEL
IREX-1.0.0.dist-info/top_level.txt
IREX-1.0.0.dist-info/RECORD
