Metadata-Version: 2.1
Name: IREX
Version: 1.0.0
Requires-Dist: joblib (>=1.1.0)
Requires-Dist: dice-ml (>=0.8)
Requires-Dist: shap (>=0.41.0)
Requires-Dist: lime (>=0.2.0.1)
Requires-Dist: seaborn (>=0.11.2)
Requires-Dist: pandas (>=1.4.3)
Requires-Dist: matplotlib (>=3.5.2)
Requires-Dist: matplotlib-inline (>=0.1.3)
Requires-Dist: numpy (>=1.16.0)
Requires-Dist: sklearn (>=0.0)
Requires-Dist: explainerdashboard (>=0.4.0)
Requires-Dist: imblearn (>=0.0)
Requires-Dist: alibi (>=0.7.0)
